[
  {
    "n": 1,
    "id": 2720181,
    "title": "Nuevos votantes. Axel Kicillof elevó casi un 25% el padrón de extranjeros",
    "url": "https://www.lanacion.com.ar/politica/axel-kicillof-elevo-casi-un-25-el-padron-extranjero-en-la-provincia-de-buenos-aires-nid04062021/",
    "image": "https://bucket1.glanacion.com/anexos/fotos/12/3790212.jpg"
  },
  {
    "n": 2,
    "id": 2720152,
    "title": "Análisis. ''No rompan nada'', el plan en marcha del oficialismo",
    "url": "https://www.lanacion.com.ar/politica/no-rompan-nada-el-plan-en-marcha-del-oficialismo-nid04062021/",
    "image": "https://bucket1.glanacion.com/anexos/fotos/67/3790167.jpg"
  },
  {
    "n": 3,
    "id": 2720505,
    "title": "Candidaturas. Los nombres que baraja el oficialismo y el comodín de Scioli",
    "url": "https://www.lanacion.com.ar/politica/candidaturas-los-nombres-que-baraja-el-oficialismo-y-la-carta-de-scioli-como-un-comodin-nid04062021/",
    "image": "https://bucket1.glanacion.com/anexos/fotos/39/3790539.jpg"
  },
  {
    "n": 4,
    "id": 2720180,
    "title": "Sputnik V. Para fin de mes, 2,4 millones de personas deberían recibir la 2° dosis",
    "url": "https://www.lanacion.com.ar/sociedad/mision-imposible-24-millones-de-personas-esperan-la-2-dosis-de-sputnik-v-nid04062021/",
    "image": "https://bucket1.glanacion.com/anexos/fotos/11/3790211.jpg"
  },
  {
    "n": 5,
    "id": 2720142,
    "title": "Covid. Cómo sacar turno de vacunación para personas de 55 a 59 años",
    "url": "https://www.lanacion.com.ar/sociedad/como-sacar-turno-de-vacunas-contra-el-covid-para-personas-de-55-a-59-anos-en-caba-nid04062021/",
    "image": "https://bucket1.glanacion.com/anexos/fotos/45/3790145.jpg"
  },
  {
    "n": 6,
    "id": 2720138,
    "title": "NBA. Con un gran tapón de Campazzo, Denver eliminó a Portland y está en cuartos",
    "url": "https://www.lanacion.com.ar/deportes/basquetbol/facundo-campazzo-volvio-a-rendir-bien-y-denver-nuggets-elimino-a-portland-trail-blazers-y-esta-en-nid03062021/",
    "image": "https://bucket1.glanacion.com/anexos/fotos/31/3790131.jpg"
  },
  {
    "n": 7,
    "id": 2720137,
    "title": "Lección. ¿Más fuerte, más alto, más lejos? La selección aprende a la fuerza",
    "url": "https://www.lanacion.com.ar/deportes/futbol/argentina-chile-la-seleccion-de-messi-y-una-leccion-repetida-correr-mas-rapido-no-la-lleva-adonde-nid03062021/",
    "image": "https://bucket1.glanacion.com/anexos/fotos/26/3790126.jpg"
  },
  {
    "n": 8,
    "id": 2719991,
    "title": "Posiciones. Así está la tabla de las eliminatorias sudamericanas para Qatar 2022",
    "url": "https://www.lanacion.com.ar/deportes/futbol/posiciones-de-las-eliminatorias-sudamericanas-qatar-2022-nid03062021/",
    "image": "https://bucket1.glanacion.com/anexos/fotos/07/3789907.jpg"
  },
  {
    "n": 9,
    "id": 2720160,
    "title": "Rareza. Un registro de Messi que no es positivo para la selección",
    "url": "https://www.lanacion.com.ar/deportes/solo-de-penal-una-rareza-de-messi-que-no-es-positiva-para-la-seleccion-nid04062021/",
    "image": "https://bucket1.glanacion.com/anexos/fotos/83/3790183.jpg"
  },
  {
    "n": 10,
    "id": 2719845,
    "title": "Covid. Cómo serán las restricciones para el fin de semana en CABA y provincia",
    "url": "https://www.lanacion.com.ar/sociedad/como-seran-las-restricciones-por-covid-en-caba-y-provincia-de-buenos-aires-este-fin-de-semana-del-5-nid03062021/",
    "image": "https://bucket1.glanacion.com/anexos/fotos/97/3789297.jpeg"
  },
  {
    "n": 11,
    "id": 2719884,
    "title": "Encendido discurso. Vacunas: la dura respuesta de un senador opositor a Cafiero",
    "url": "https://www.lanacion.com.ar/politica/vacunas-la-dura-respuesta-de-un-senador-opositor-a-santiago-cafiero-nid03062021/",
    "image": "https://bucket1.glanacion.com/anexos/fotos/53/3789953.jpg"
  },
  {
    "n": 12,
    "id": 2720093,
    "title": "Denuncia. Elisa Carrió: ''Cristina Kirchner trabaja para Sputnik''",
    "url": "https://www.lanacion.com.ar/politica/elisa-carrio-cristina-kirchner-trabaja-para-sputnik-nid03062021/",
    "image": "https://bucket1.glanacion.com/anexos/fotos/84/3790084.jpg"
  },
  {
    "n": 13,
    "id": 2720136,
    "title": "Entrevista. Vidal: \"Macri me pidió que fuera candidata en la provincia\"",
    "url": "https://www.lanacion.com.ar/politica/maria-eugenia-vidal-tiro-un-mensaje-interno-y-le-hizo-un-guino-a-una-candidatura-portena-nid03062021/",
    "image": "https://bucket1.glanacion.com/anexos/fotos/43/3790143.jpg"
  },
  {
    "n": 14,
    "id": 2720154,
    "title": "Congreso. Lousteau atribuyó el enojo de Cafiero a Cristina Kirchner",
    "url": "https://www.lanacion.com.ar/politica/martin-lousteau-santiago-cafiero-en-el-senado-siente-que-rinde-examen-frente-a-cristina-kirchner-nid04062021/",
    "image": "https://bucket1.glanacion.com/anexos/fotos/68/3790168.jpg"
  },
  {
    "n": 15,
    "id": 2720494,
    "title": "La cuestionada estrategia de vacunación que muestra buenos resultados",
    "url": "https://www.lanacion.com.ar/el-mundo/la-cuestionada-estrategia-de-vacunacion-de-canada-que-muestra-buenos-resultados-nid04062021/",
    "image": "https://bucket1.glanacion.com/anexos/fotos/28/3790528.jpg"
  },
  {
    "n": 16,
    "id": 2720182,
    "title": "Opinión. El gobierno militar que incubó al peronismo",
    "url": "https://www.lanacion.com.ar/opinion/el-gobierno-militar-que-incubo-al-peronismo-nid04062021/",
    "image": "https://bucket1.glanacion.com/anexos/fotos/16/3790216.jpg"
  },
  {
    "n": 17,
    "id": 2719859,
    "title": "Ramón Garriga. El productor musical que se volvió loco por la masa madre",
    "url": "https://www.lanacion.com.ar/lifestyle/ramon-garriga-loco-por-la-masa-madre-nid03062021/",
    "image": "https://bucket1.glanacion.com/anexos/fotos/71/3790071.jpg"
  },
  {
    "n": 18,
    "id": 2720050,
    "title": "Nació en Rusia. Vive en Argentina y tiene récords en una actividad que sorprende",
    "url": "https://www.lanacion.com.ar/lifestyle/nacio-en-rusia-vive-en-la-argentina-tiene-records-en-paracaidismo-y-fabrica-sombreros-que-son-furor-nid03062021/",
    "image": "https://bucket1.glanacion.com/anexos/fotos/11/3790011.jpeg"
  },
  {
    "n": 19,
    "id": 2719803,
    "title": "AFIP. Trasladan los vencimientos de Ganancias y Bienes Personales",
    "url": "https://www.lanacion.com.ar/economia/afip-trasladan-a-julio-los-vencimientos-de-ganancias-y-bienes-personales-nid03062021/",
    "image": "https://bucket1.glanacion.com/anexos/fotos/20/3789220.jpg"
  },
  {
    "n": 20,
    "id": 2719949,
    "title": "Furor en TikTok. La historia del joven que se burla de los influencers",
    "url": "https://www.lanacion.com.ar/lifestyle/de-desempleado-a-furor-en-tiktok-la-historia-del-joven-que-se-burla-de-los-influencers-nid03062021/",
    "image": "https://bucket1.glanacion.com/anexos/fotos/06/3789806.png"
  },
  {
    "n": 21,
    "id": 2720126,
    "title": "Se agravó. El último parte médico de Carlos Reutemann",
    "url": "https://www.lanacion.com.ar/politica/el-ultimo-parte-medico-de-carlos-reutemann-nid03062021/",
    "image": "https://bucket1.glanacion.com/anexos/fotos/12/3790112.jpg"
  },
  {
    "n": 22,
    "id": 2720011,
    "title": "Rosario. Una mujer de 33 años murió de Covid luego de dar a luz",
    "url": "https://www.lanacion.com.ar/sociedad/una-mujer-de-33-anos-murio-de-covid-luego-de-dar-a-luz-nid03062021/",
    "image": "https://bucket1.glanacion.com/anexos/fotos/55/3789955.jpg"
  },
  {
    "n": 23,
    "id": 2719649,
    "title": "Tenía 31 años. El conmovedor posteo de Agustina en Instagram antes de morir",
    "url": "https://www.lanacion.com.ar/espectaculos/el-conmovedor-posteo-de-agustina-de-bake-off-en-instagram-antes-de-morir-que-nadie-te-diga-que-es-nid03062021/",
    "image": "https://bucket1.glanacion.com/anexos/fotos/54/3788954.png"
  },
  {
    "n": 24,
    "id": 2719881,
    "title": "Por primera vez. Candela Ruggeri, en su departamento, posa con su novio",
    "url": "https://www.lanacion.com.ar/revista-hola/candela-ruggeri-en-su-departamento-de-nunez-posa-por-primera-vez-con-su-novio-nid03062021/",
    "image": "https://bucket1.glanacion.com/anexos/fotos/16/3789416.jpg"
  },
  {
    "n": 25,
    "id": 2720170,
    "title": "Análisis. El escenario económico más temido",
    "url": "https://www.lanacion.com.ar/opinion/el-escenario-economico-mas-temido-nid04062021/",
    "image": "https://bucket1.glanacion.com/anexos/fotos/98/3790198.jpeg"
  },
  {
    "n": 26,
    "id": 2720151,
    "title": "Desconfianza y pujas de poder impiden los proyectos de país",
    "url": "https://www.lanacion.com.ar/opinion/desconfianza-y-pujas-de-poder-impiden-los-proyectos-de-pais-nid04062021/"
  },
  {
    "n": 27,
    "id": 2720153,
    "title": "La estrategia sanitaria argentina contra el Covid: las lecciones de Clausewitz",
    "url": "https://www.lanacion.com.ar/opinion/la-estrategia-sanitaria-argentina-contra-el-covid-las-lecciones-de-clausewitz-nid04062021/"
  },
  {
    "n": 28,
    "id": 2720150,
    "title": "El viaje de Pablo Moyano al centro del kirchnerismo",
    "url": "https://www.lanacion.com.ar/opinion/el-viaje-de-pablo-moyano-al-centro-del-kirchnerismo-nid04062021/"
  },
  {
    "n": 29,
    "id": 2720157,
    "title": "El respeto a los símbolos patrios",
    "url": "https://www.lanacion.com.ar/editoriales/el-respeto-a-los-simbolos-patrios-nid04062021/"
  },
  {
    "n": 30,
    "id": 2720148,
    "title": "Colombia y Venezuela, una frontera caliente",
    "url": "https://www.lanacion.com.ar/editoriales/colombia-y-venezuela-una-frontera-caliente-nid04062021/"
  },
  {
    "n": 31,
    "id": 2720091,
    "title": "Sputnik V. Llegó el vuelo que más vacunas trajo desde Moscú",
    "url": "https://www.lanacion.com.ar/sociedad/llego-un-nuevo-vuelo-desde-moscu-con-815150-dosis-de-la-sputnik-v-nid03062021/",
    "image": "https://bucket1.glanacion.com/anexos/fotos/74/3790074.jpeg"
  },
  {
    "n": 32,
    "id": 2718570,
    "title": "Boletín Oficial. Cuándo serán las PASO y las elecciones generales",
    "url": "https://www.lanacion.com.ar/politica/es-ley-la-postergacion-por-cinco-semanas-de-las-elecciones-nid02062021/",
    "image": "https://bucket1.glanacion.com/anexos/fotos/54/3787754.jpg"
  },
  {
    "n": 33,
    "id": 2720020,
    "title": "Coronavirus. Qué se sabe de la variante híbrida de Vietnam",
    "url": "https://www.lanacion.com.ar/el-mundo/coronavirus-que-se-sabe-de-la-nueva-variante-hibrida-de-vietnam-nid03062021/",
    "image": "https://bucket1.glanacion.com/anexos/fotos/63/3789963.jpg"
  },
  {
    "n": 34,
    "id": 2719973,
    "title": "Núñez. Música y whisky con gaseosa antes del crimen de las 22 puñaladas",
    "url": "https://www.lanacion.com.ar/seguridad/nunez-antes-del-homicidio-de-las-22-punaladas-las-sospechosas-escucharon-musica-a-todo-volumen-y-nid03062021/",
    "image": "https://bucket1.glanacion.com/anexos/fotos/81/3789881.jpg"
  },
  {
    "n": 35,
    "id": 2720049,
    "title": "Dunkerque. El milagro que salvó a los aliados de una matanza nazi",
    "url": "https://www.lanacion.com.ar/el-mundo/dunkerque-el-milagro-que-salvo-a-los-aliados-de-una-matanza-nazi-nid03062021/",
    "image": "https://bucket1.glanacion.com/anexos/fotos/00/3790000.jpg"
  },
  {
    "n": 36,
    "id": 2719696,
    "title": "David Carradine. Una leyenda que mantuvo el halo de misterio hasta en su muerte",
    "url": "https://www.lanacion.com.ar/espectaculos/personajes/david-carradine-una-leyenda-de-hollywood-que-conservo-el-halo-de-misterio-hasta-en-su-muerte-nid03062021/",
    "image": "https://bucket1.glanacion.com/anexos/fotos/59/3789059.png"
  },
  {
    "n": 37,
    "id": 2720167,
    "title": "Luis Miguel, la serie. Michelle Salas acusó a los creadores",
    "url": "https://www.lanacion.com.ar/espectaculos/personajes/michelle-salas-acuso-a-los-creadores-de-luis-miguel-la-serie-de-sexualizar-a-su-personaje-y-violar-nid04062021/",
    "image": "https://bucket1.glanacion.com/anexos/fotos/93/3790193.jpg"
  },
  {
    "n": 38,
    "id": 2719851,
    "title": "''Oro flotante''. Encontraron ámbar gris en una ballena y ahora son millonarios",
    "url": "https://www.lanacion.com.ar/lifestyle/oro-flotante-pescadores-encontraron-ambar-gris-adentro-de-una-ballena-y-se-volvieron-millonarios-nid03062021/",
    "image": "https://bucket1.glanacion.com/anexos/fotos/03/3789303.jpg"
  },
  {
    "n": 39,
    "id": 2719965,
    "title": "Realeza. El apodo secreto que el príncipe Carlos le puso a Meghan Markle",
    "url": "https://www.lanacion.com.ar/lifestyle/el-apodo-secreto-que-el-principe-carlos-le-puso-a-meghan-markle-nid03062021/",
    "image": "https://bucket1.glanacion.com/anexos/fotos/68/3789868.jpg"
  },
  {
    "n": 40,
    "id": 2719734,
    "title": "\"Es insultante''. El enojo de una vegana por un mensaje ofensivo en un menú",
    "url": "https://www.lanacion.com.ar/lifestyle/es-insultante-el-enojo-de-una-vegana-tras-recibir-un-mensaje-ofensivo-en-el-menu-de-un-restaurante-nid03062021/",
    "image": "https://bucket1.glanacion.com/anexos/fotos/99/3789099.jpg"
  },
  {
    "n": 41,
    "id": 2613211,
    "title": "\"No te enamores\". Una advertencia a tiempo no pudo frenar su historia de amor",
    "url": "https://www.lanacion.com.ar/lifestyle/poco-ortodoxa-el-entorno-la-rechazo-quedo-embarazada-y-sucedio-lo-inesperado-nid25022021/",
    "image": "https://bucket1.glanacion.com/anexos/fotos/95/3789995.jpg"
  },
  {
    "n": 42,
    "id": 2719940,
    "title": "A los 19 años. Una actriz de The Office fue coronada ''princesa del Ku Klux Klan''",
    "url": "https://www.lanacion.com.ar/espectaculos/polemica-una-actriz-de-the-office-fue-coronada-princesa-del-ku-klux-klan-a-los-19-anos-nid03062021/",
    "image": "https://bucket1.glanacion.com/anexos/fotos/83/3789783.jpg"
  },
  {
    "n": 43,
    "id": 2720185,
    "title": "Análisis. Un gobierno ''obsesionado'' con quitarse culpas",
    "url": "https://www.lanacion.com.ar",
    "image": "https://bucket1.glanacion.com/anexos/fotos/19/3790219.jpg"
  },
  {
    "n": 44,
    "id": 2720065,
    "title": "Opinión. Sergio Massa es más cristinista que Cristina",
    "url": "https://www.lanacion.com.ar/espectaculos/alfredo-leuco-sergio-massa-es-mas-cristinista-que-cristina-nid03062021/",
    "image": "https://bucket1.glanacion.com/anexos/fotos/57/3790057.jpg"
  },
  {
    "n": 45,
    "id": 2719951,
    "title": "''¡Lean lo que votan!''. El fuerte cruce entre Cafiero y Naidenoff",
    "url": "https://www.lanacion.com.ar/politica/lean-lo-que-votan-fuerte-cruce-entre-cafiero-y-naidenoff-nid03062021/",
    "image": "https://bucket1.glanacion.com/anexos/fotos/18/3789818.jpg"
  },
  {
    "n": 46,
    "id": 2720040,
    "title": "2023. La promesa que se hicieron Larreta y Vidal ante dirigentes bonaerenses",
    "url": "https://www.lanacion.com.ar/politica/la-promesa-de-horacio-rodriguez-larreta-y-maria-eugenia-vidal-en-una-cumbre-con-dirigentes-de-pro-nid03062021/",
    "image": "https://bucket1.glanacion.com/anexos/fotos/84/3789984.jpeg"
  },
  {
    "n": 47,
    "id": 2719817,
    "title": "Elecciones. Alberto Fernández y un guiño a la UCR en un acto",
    "url": "https://www.lanacion.com.ar/politica/mendoza-alberto-fernandez-pidio-que-la-grieta-no-postergue-el-desarrollo-de-la-argentina-nid03062021/",
    "image": "https://bucket1.glanacion.com/anexos/fotos/34/3789234.jpg"
  },
  {
    "n": 48,
    "id": 2716838,
    "title": "Autos 0km. Cuáles fueron los modelos más vendidos de mayo y sus precios",
    "url": "https://www.lanacion.com.ar/autos/al-volante/precios-y-versiones-de-los-autos-mas-vendidos-de-mayo-nid01062021/",
    "image": "https://bucket1.glanacion.com/anexos/fotos/92/3785592.jpg"
  },
  {
    "n": 49,
    "id": 2719606,
    "title": "Aguinaldo. Las mejores opciones para para invertir y no perder con la inflación",
    "url": "https://www.lanacion.com.ar/economia/como-invertir-mejor-el-aguinaldo-las-opciones-que-recomiendan-los-especialistas-nid03062021/",
    "image": "https://bucket1.glanacion.com/anexos/fotos/83/3788883.jpg"
  },
  {
    "n": 50,
    "id": 2719752,
    "title": "Cepo. Los frigoríficos alertan que se necesita una rápida solución",
    "url": "https://www.lanacion.com.ar/economia/campo/cepo-a-la-carne-los-frigorificos-alertan-que-se-necesita-una-rapida-solucion-nid03062021/",
    "image": "https://bucket1.glanacion.com/anexos/fotos/30/3789130.jpg"
  },
  {
    "n": 51,
    "id": 2720051,
    "title": "Amigovios. Una quinta, romances infantiles y el debut de Nicole como cantante",
    "url": "https://www.lanacion.com.ar/espectaculos/television/amigovios-una-quinta-en-parque-leloir-romances-infantiles-y-el-debut-y-despedida-de-nicole-neumann-nid04062021/",
    "image": "https://bucket1.glanacion.com/anexos/fotos/15/3790015.jpg"
  },
  {
    "n": 52,
    "id": 2720052,
    "title": "Qué es de la vida de... Catherine Bach, la actriz que impuso su estilo en los 80",
    "url": "https://www.lanacion.com.ar/espectaculos/que-es-de-la-vida-de-catherine-bach-la-actriz-que-impuso-su-propio-estilo-en-la-moda-de-los-80-nid04062021/",
    "image": "https://bucket1.glanacion.com/anexos/fotos/30/3790030.jpg"
  },
  {
    "n": 53,
    "id": 2720042,
    "title": "TV. Horacio Cabak desmiente los dichos de Gustavo Sofovich",
    "url": "https://www.lanacion.com.ar/espectaculos/personajes/horacio-cabak-desmiente-los-dichos-de-gustavo-sofovich-nid03062021/",
    "image": "https://bucket1.glanacion.com/anexos/fotos/87/3789987.jpg"
  },
  {
    "n": 54,
    "id": 2719964,
    "title": "Jugate conmigo. Hace 30 años nacía el gran éxito creado por Cris Morena",
    "url": "https://www.lanacion.com.ar/espectaculos/television/jugate-conmigo-hace-30-anos-nacia-el-gran-exito-creado-por-cris-morena-nid03062021/",
    "image": "https://bucket1.glanacion.com/anexos/fotos/65/3789865.jpg"
  },
  {
    "n": 55,
    "id": 2719975,
    "title": "Música. Jimena Barón contó qué expareja se refiere en su nueva canción",
    "url": "https://www.lanacion.com.ar/espectaculos/personajes/jimena-baron-revelo-a-que-expareja-se-refiere-en-su-nueva-cancion-nid03062021/",
    "image": "https://bucket1.glanacion.com/anexos/fotos/90/3789890.png"
  },
  {
    "n": 56,
    "id": 2719916,
    "title": "Pink Floyd. Roger Waters reveló los textos que David Gilmour no quiso publicar",
    "url": "https://www.lanacion.com.ar/espectaculos/musica/roger-water-revelo-los-textos-que-david-gilmour-no-quiso-que-se-publicaran-en-la-reedicion-de-un-nid03062021/",
    "image": "https://bucket1.glanacion.com/anexos/fotos/88/3789488.jpg"
  },
  {
    "n": 57,
    "id": 2720073,
    "title": "Camiseta. Homenaje a medias de la selección a Maradona por el rechazo de la FIFA",
    "url": "https://www.lanacion.com.ar/deportes/futbol/argentina-chile-la-camiseta-con-la-que-el-seleccionado-argentino-homenajeo-a-diego-maradona-nid03062021/",
    "image": "https://bucket1.glanacion.com/anexos/fotos/61/3790061.jpg"
  },
  {
    "n": 58,
    "id": 2720127,
    "title": "Insólito. Ahora Brasil puede quedarse sin las figuras en su propia Copa América",
    "url": "https://www.lanacion.com.ar/deportes/futbol/insolito-brasil-podria-no-contar-con-sus-figuras-en-su-propia-copa-america-nid03062021/",
    "image": "https://bucket1.glanacion.com/anexos/fotos/13/3790113.jpg"
  },
  {
    "n": 59,
    "id": 2720144,
    "title": "Tenis nocturno. La queja de Rafael Nadal a Roland Garros",
    "url": "https://www.lanacion.com.ar/deportes/tenis/roland-garros-de-noche-un-programa-con-figuras-de-lujo-que-todavia-esta-lejos-de-ser-el-gran-show-nid04062021/",
    "image": "https://bucket1.glanacion.com/anexos/fotos/47/3790147.jpg"
  },
  {
    "n": 60,
    "id": 2719974,
    "title": "Negocios. 20 claves para entender qué está pasando en el mercado inmobiliario",
    "url": "https://www.lanacion.com.ar/propiedades/casas-y-departamentos/propiedades-20-claves-para-entender-que-esta-pasando-en-el-mercado-inmobiliario-nid03062021/",
    "image": "https://bucket1.glanacion.com/anexos/fotos/86/3789886.jpg"
  },
  {
    "n": 61,
    "id": 2719985,
    "title": "Madrid. Cristiano Ronaldo abrirá un hotel de lujo en la Gran Vía",
    "url": "https://www.lanacion.com.ar/propiedades/inmuebles-comerciales/madrid-cristiano-ronaldo-abrira-un-hotel-de-lujo-en-la-gran-via-nid03062021/",
    "image": "https://bucket1.glanacion.com/anexos/fotos/98/3789898.jpg"
  },
  {
    "n": 62,
    "id": 2719647,
    "title": "Chau Chascomús. Dejó su restaurante italiano y abrió uno de empanadas en Roma",
    "url": "https://www.lanacion.com.ar/revista-lugares/dejo-su-restaurante-italiano-en-chascomus-y-abrio-uno-argentino-en-roma-nid03062021/",
    "image": "https://bucket1.glanacion.com/anexos/fotos/42/3788942.jpg"
  },
  {
    "n": 63,
    "id": 2718761,
    "title": "Horóscopo: ¿qué dice tu ascendente para hoy y el fin de semana del 4 de junio?",
    "url": "https://www.lanacion.com.ar/lifestyle/horoscopo-que-dice-tu-ascendente-para-hoy-y-el-fin-de-semana-del-4-de-junio-nid02062021/",
    "image": "https://bucket1.glanacion.com/anexos/fotos/76/3787976.jpg"
  },
  {
    "n": 64,
    "id": 2719666,
    "title": "Lo sustentable. Más en boga que nunca: cinco beneficios eco friendly",
    "url": "https://www.lanacion.com.ar/lifestyle/lo-sustentable-mas-en-boga-que-nunca-cinco-beneficios-eco-friendly-nid03062021/",
    "image": "https://bucket1.glanacion.com/anexos/fotos/80/3788980.png"
  },
  {
    "n": 65,
    "id": 2381248,
    "title": "Crisis de 1989. Del salariazo y las privatizaciones a la convertibilidad en 1991",
    "image": "https://bucket1.glanacion.com/anexos/fotos/91/3768891.jpg"
  },
  {
    "n": 66,
    "id": 2712013,
    "title": "Redes solidarias. Cómo un influencer terminó llevando atletas al Sudamericano",
    "url": "https://www.lanacion.com.ar/sociedad/por-que-santiago-maratea-debio-organizar-la-campana-para-llevar-atletas-al-campeonato-sudamericano-nid28052021/",
    "image": "https://bucket1.glanacion.com/anexos/fotos/31/3779431.png"
  },
  {
    "n": 67,
    "id": 2719954,
    "title": "100 argentinos dicen. El parecido de un participante con el cantante de Marama",
    "url": "https://www.lanacion.com.ar/espectaculos/el-parecido-de-un-participante-con-el-cantante-de-marama-que-barassi-no-dejo-pasar-nid03062021/",
    "image": "https://bucket1.glanacion.com/anexos/fotos/40/3789840.jpg"
  },
  {
    "n": 68,
    "id": 2719860,
    "title": "Desafío. Diego Boneta protagonizará otra biopic tras interpretar a Luis Miguel",
    "url": "https://www.lanacion.com.ar/espectaculos/diego-boneta-protagonizara-otra-biopic-tras-el-exito-de-la-serie-de-luis-miguel-nid03062021/",
    "image": "https://bucket1.glanacion.com/anexos/fotos/35/3789335.jpg"
  },
  {
    "n": 69,
    "id": 2720005,
    "title": "Bitcoin. Quién es quién en la guerra de las criptomonedas",
    "url": "https://www.lanacion.com.ar/tecnologia/bitcoin-quien-es-quien-en-la-guerra-de-las-criptomonedas-y-como-te-puede-afectar-nid03062021/",
    "image": "https://bucket1.glanacion.com/anexos/fotos/40/3789940.jpg"
  }
]